magic_cta_pipe-0.6.1.dist-info/licenses/LICENSE
magicctapipe/__init__.py
magicctapipe/_version.py
magicctapipe/conftest.py
magicctapipe/version.py
magicctapipe/image/__init__.py
magicctapipe/image/calib.py
magicctapipe/image/cleaning.py
magicctapipe/image/leakage.py
magicctapipe/image/muons/__init__.py
magicctapipe/image/muons/muon_analysis.py
magicctapipe/io/__init__.py
magicctapipe/io/containers.py
magicctapipe/io/gadf.py
magicctapipe/io/io.py
magicctapipe/reco/__init__.py
magicctapipe/reco/estimators.py
magicctapipe/resources/LST_runs.txt
magicctapipe/resources/MAGIC_runs.txt
magicctapipe/resources/config.yaml
magicctapipe/resources/database_config.yaml
magicctapipe/resources/test_config.yaml
magicctapipe/resources/test_config_auto_MCP.yaml
magicctapipe/resources/test_config_auto_MCP_4LST.yaml
magicctapipe/resources/test_config_calib.yaml
magicctapipe/resources/test_config_monly.yaml
magicctapipe/scripts/__init__.py
magicctapipe/scripts/lst1_magic/__init__.py
magicctapipe/scripts/lst1_magic/coincident_brokenGPS.py
magicctapipe/scripts/lst1_magic/create_dl3_index_files.py
magicctapipe/scripts/lst1_magic/lst1_magic_cloud_profile_estimator.py
magicctapipe/scripts/lst1_magic/lst1_magic_create_irf.py
magicctapipe/scripts/lst1_magic/lst1_magic_dl1_stereo_to_dl2.py
magicctapipe/scripts/lst1_magic/lst1_magic_dl2_to_dl3.py
magicctapipe/scripts/lst1_magic/lst1_magic_event_coincidence.py
magicctapipe/scripts/lst1_magic/lst1_magic_mc_dl0_to_dl1.py
magicctapipe/scripts/lst1_magic/lst1_magic_mc_muon_analysis.py
magicctapipe/scripts/lst1_magic/lst1_magic_stereo_reco.py
magicctapipe/scripts/lst1_magic/lst1_magic_train_rfs.py
magicctapipe/scripts/lst1_magic/lst_m1_m2_cloud_correction.py
magicctapipe/scripts/lst1_magic/magic_calib_to_dl1.py
magicctapipe/scripts/lst1_magic/merge_hdf_files.py
magicctapipe/scripts/lst1_magic/muon_analysis_LST_or_MAGIC_data.py
magicctapipe/scripts/lst1_magic/tune_magic_nsb.py
magicctapipe/scripts/lst1_magic/semi_automatic_scripts/DL1_to_DL2.py
magic_cta_pipe-0.6.1.dist-info/METADATA
magic_cta_pipe-0.6.1.dist-info/WHEEL
magic_cta_pipe-0.6.1.dist-info/entry_points.txt
magic_cta_pipe-0.6.1.dist-info/top_level.txt
magic_cta_pipe-0.6.1.dist-info/RECORD
